cu2qu/__init__.py
cu2qu/__main__.py
cu2qu/_version.py
cu2qu/cli.py
cu2qu/cu2qu.py
cu2qu/cython.py
cu2qu/errors.py
cu2qu/pens.py
cu2qu/ufo.py
cu2qu-1.6.7.post2.dist-info/LICENSE
cu2qu-1.6.7.post2.dist-info/METADATA
cu2qu-1.6.7.post2.dist-info/WHEEL
cu2qu-1.6.7.post2.dist-info/entry_points.txt
cu2qu-1.6.7.post2.dist-info/top_level.txt
cu2qu-1.6.7.post2.dist-info/RECORD
